unasync/__init__.py
unasync/_version.py
unasync-0.6.0.dist-info/LICENSE
unasync-0.6.0.dist-info/LICENSE.APACHE2
unasync-0.6.0.dist-info/LICENSE.MIT
unasync-0.6.0.dist-info/METADATA
unasync-0.6.0.dist-info/WHEEL
unasync-0.6.0.dist-info/top_level.txt
unasync-0.6.0.dist-info/RECORD
